odoo/addons/product_harmonized_system_stock/README.rst
odoo/addons/product_harmonized_system_stock/__init__.py
odoo/addons/product_harmonized_system_stock/__manifest__.py
odoo/addons/product_harmonized_system_stock/i18n/es.po
odoo/addons/product_harmonized_system_stock/i18n/product_harmonized_system_stock.pot
odoo/addons/product_harmonized_system_stock/i18n/sl.po
odoo/addons/product_harmonized_system_stock/readme/CONTRIBUTORS.rst
odoo/addons/product_harmonized_system_stock/readme/DESCRIPTION.rst
odoo/addons/product_harmonized_system_stock/static/description/icon.png
odoo/addons/product_harmonized_system_stock/static/description/index.html
odoo/addons/product_harmonized_system_stock/views/hs_code_menu.xml
odoo12_addon_product_harmonized_system_stock-12.0.1.0.0.99.dev10.dist-info/METADATA
odoo12_addon_product_harmonized_system_stock-12.0.1.0.0.99.dev10.dist-info/WHEEL
odoo12_addon_product_harmonized_system_stock-12.0.1.0.0.99.dev10.dist-info/top_level.txt
odoo12_addon_product_harmonized_system_stock-12.0.1.0.0.99.dev10.dist-info/RECORD
